[{"category": "OTHER", "createdAt": 1754836175810, "durability": -1, "expireAt": 1755095375810, "item": {"meta": 0, "name": "sulfuricwater", "quantity": 1}, "name": "Fake Water", "price": 100, "pricePb": 0, "renamed": false, "seller": "820c5f51-4d1a-4d63-ba6c-1126cc96ae58", "skin": 0, "slot": 1, "type": "ITEM"}, {"category": "OTHER", "createdAt": 1754836179624, "durability": -1, "expireAt": 1755095379624, "item": {"meta": 0, "name": "sulfuricwater", "quantity": 1}, "name": "Fake Water", "price": 100, "pricePb": 0, "renamed": false, "seller": "820c5f51-4d1a-4d63-ba6c-1126cc96ae58", "skin": 0, "slot": 2, "type": "ITEM"}, {"category": "OTHER", "createdAt": 1754836183069, "durability": -1, "expireAt": 1755095383069, "item": {"meta": 0, "name": "sulfuricwater", "quantity": 1}, "name": "Fake Water", "price": 100, "pricePb": 0, "renamed": false, "seller": "820c5f51-4d1a-4d63-ba6c-1126cc96ae58", "skin": 0, "slot": 3, "type": "ITEM"}, {"category": "OTHER", "createdAt": 1754836186311, "durability": -1, "expireAt": 1755095386311, "item": {"meta": 0, "name": "sulfuricwater", "quantity": 1}, "name": "Fake Water", "price": 100, "pricePb": 0, "renamed": false, "seller": "820c5f51-4d1a-4d63-ba6c-1126cc96ae58", "skin": 0, "slot": 4, "type": "ITEM"}, {"category": "OTHER", "createdAt": 1754836189623, "durability": -1, "expireAt": 1755095389623, "item": {"meta": 0, "name": "sulfuricwater", "quantity": 1}, "name": "Fake Water", "price": 100, "pricePb": 0, "renamed": false, "seller": "820c5f51-4d1a-4d63-ba6c-1126cc96ae58", "skin": 0, "slot": 5, "type": "ITEM"}, {"category": "OTHER", "createdAt": 1754836192829, "durability": -1, "expireAt": 1755095392829, "item": {"meta": 0, "name": "sulfuricwater", "quantity": 1}, "name": "Fake Water", "price": 100, "pricePb": 0, "renamed": false, "seller": "820c5f51-4d1a-4d63-ba6c-1126cc96ae58", "skin": 0, "slot": 6, "type": "ITEM"}, {"category": "OTHER", "createdAt": 1754836195935, "durability": -1, "expireAt": 1755095395935, "item": {"meta": 0, "name": "sulfuricwater", "quantity": 1}, "name": "Fake Water", "price": 100, "pricePb": 0, "renamed": false, "seller": "820c5f51-4d1a-4d63-ba6c-1126cc96ae58", "skin": 0, "slot": 7, "type": "ITEM"}, {"category": "OTHER", "createdAt": 1754836198982, "durability": -1, "expireAt": 1755095398982, "item": {"meta": 0, "name": "sulfuricwater", "quantity": 1}, "name": "Fake Water", "price": 100, "pricePb": 0, "renamed": false, "seller": "820c5f51-4d1a-4d63-ba6c-1126cc96ae58", "skin": 0, "slot": 8, "type": "ITEM"}, {"category": "OTHER", "createdAt": 1754836201904, "durability": -1, "expireAt": 1755095401904, "item": {"meta": 0, "name": "sulfuricwater", "quantity": 1}, "name": "Fake Water", "price": 100, "pricePb": 0, "renamed": false, "seller": "820c5f51-4d1a-4d63-ba6c-1126cc96ae58", "skin": 0, "slot": 9, "type": "ITEM"}, {"category": "OTHER", "createdAt": 1754836205101, "durability": -1, "expireAt": 1755095405101, "item": {"meta": 0, "name": "sulfuricwater", "quantity": 1}, "name": "Fake Water", "price": 100, "pricePb": 0, "renamed": false, "seller": "820c5f51-4d1a-4d63-ba6c-1126cc96ae58", "skin": 0, "slot": 10, "type": "ITEM"}]